motorhead/__init__.py
motorhead/aggregation.py
motorhead/bound_method_wrapper.py
motorhead/delete_rule.py
motorhead/model/__init__.py
motorhead/model/deleteresultmodel.py
motorhead/model/document.py
motorhead/model/objectid.py
motorhead/model/utcdatetime.py
motorhead/operator.py
motorhead/py.typed
motorhead/query.py
motorhead/service.py
motorhead/typing.py
motorhead/validator.py
motorhead-0.2501.2.dist-info/LICENSE
motorhead-0.2501.2.dist-info/METADATA
motorhead-0.2501.2.dist-info/WHEEL
motorhead-0.2501.2.dist-info/RECORD
