Metadata-Version: 2.3
Name: motorhead
Version: 0.2501.2
Summary: Async MongoDB with vanilla Pydantic v2+ - made easy.
License: MIT
Author: Peter Volf
Author-email: do.volfp@gmail.com
Requires-Python: >=3.10
Classifier: Intended Audience :: Information Technology
Classifier: Operating System :: OS Independent
Classifier: Programming Language :: Python :: 3
Classifier: Development Status :: 4 - Beta
Classifier: Topic :: Internet
Classifier: Topic :: Software Development :: Libraries
Classifier: Topic :: Software Development
Classifier: Typing :: Typed
Classifier: Environment :: Web Environment
Classifier: Framework :: FastAPI
Classifier: Intended Audience :: Developers
Classifier: License :: OSI Approved :: MIT License
Classifier: Topic :: Internet :: WWW/HTTP
Requires-Dist: motor
Requires-Dist: pydantic
Project-URL: Documentation, https://volfpeter.github.io/motorhead
Project-URL: Homepage, https://github.com/volfpeter/motorhead
Project-URL: tracker, https://github.com/volfpeter/motorhead/issues
